toyds/__init__.py
toyds/config.py
toyds/constants.py
toyds/core.py
toyds/data.py
toyds/download.py
toyds/model.py
toyds/modules.py
toyds/optim.py
toyds/train.py
toyds/utils.py
toyds/tasks/__init__.py
toyds/tasks/math.py
toyds/tasks/needle.py
toyds/tasks/task.py
toyds/tasks/translation.py
toyds-0.1.0.dist-info/METADATA
toyds-0.1.0.dist-info/WHEEL
toyds-0.1.0.dist-info/entry_points.txt
toyds-0.1.0.dist-info/top_level.txt
toyds-0.1.0.dist-info/RECORD
