Metadata-Version: 2.1
Name: toyds
Version: 0.1.0
Summary: Toy datasets for training sequence models
Author: Harry Coultas Blum
Project-URL: Homepage, https://github.com/mogwai/toyds
Requires-Dist: einops
Requires-Dist: torch
Requires-Dist: numpy
Requires-Dist: wandb
Requires-Dist: pydantic
Requires-Dist: tqdm
